vectorlitedb/__init__.py
vectorlitedb/db.py
vectorlitedb-0.1.0.dist-info/licenses/LICENSE
vectorlitedb-0.1.0.dist-info/METADATA
vectorlitedb-0.1.0.dist-info/WHEEL
vectorlitedb-0.1.0.dist-info/entry_points.txt
vectorlitedb-0.1.0.dist-info/top_level.txt
vectorlitedb-0.1.0.dist-info/RECORD
